gaolab_mstool-0.0.1.dist-info/licenses/LICENSE
ms_tool/__init__.py
ms_tool/expasy_rules.py
ms_tool/mstool.py
ms_tool/mzml_file_tool.py
ms_tool/raw_file_tool.py
gaolab_mstool-0.0.1.dist-info/METADATA
gaolab_mstool-0.0.1.dist-info/WHEEL
gaolab_mstool-0.0.1.dist-info/top_level.txt
gaolab_mstool-0.0.1.dist-info/RECORD
